cecmap/__init__.py
cecmap/__main__.py
cecmap/cli.py
cecmap/commands.py
cecmap/device.py
cecmap/keycodes.py
cecmap/notify.py
cecmap/config/__init__.py
cecmap/config/default.cfg
cecmap-1.0.0.data/data/lib/systemd/user/cecmap.service
cecmap-1.0.0.data/data/share/systemd/user/cecmap.service
cecmap-1.0.0.dist-info/METADATA
cecmap-1.0.0.dist-info/UNLICENSE
cecmap-1.0.0.dist-info/WHEEL
cecmap-1.0.0.dist-info/entry_points.txt
cecmap-1.0.0.dist-info/top_level.txt
cecmap-1.0.0.dist-info/zip-safe
cecmap-1.0.0.dist-info/RECORD
