Metadata-Version: 2.1
Name: cecmap
Version: 1.0.0
Summary: Maps CEC events to arbitrary keybindings for controlling your raspberrypi desktop via TV remote.
Home-page: https://github.com/coldfix/cecmap
Author: Thomas Gläßle
Author-email: thomas@coldfix.de
License: Unlicense
Keywords: cec keybindings raspberry pi raspberry-pi tv remote control
Platform: UNKNOWN
Classifier: Development Status :: 3 - Alpha
Classifier: Environment :: X11 Applications
Classifier: Intended Audience :: End Users/Desktop
Classifier: License :: OSI Approved :: The Unlicense (Unlicense)
Classifier: Operating System :: POSIX :: Linux
Classifier: Programming Language :: Python :: 3
Classifier: License :: OSI Approved :: MIT License
Classifier: Topic :: Desktop Environment
Classifier: Topic :: Multimedia
Classifier: Topic :: Utilities
Requires-Python: >=3.7
License-File: UNLICENSE
Requires-Dist: cec
Requires-Dist: pynput
Requires-Dist: notify2
